{
    "0": {
        "metadata": {
            "title": "Turan Devleti",
            "author": "Ömer Seyfettin",
            "processed_at": "2025-09-19T17:34:02"
        },
        "data": [
            [
                "<SPC>",
                8428
            ],
            [
                "a",
                6239
            ],
            [
                "e",
                4959
            ],
            [
                "i",
                4864
            ],
            [
                "r",
                4327
            ],
            [
                "l",
                3769
            ],
            [
                "n",
                3666
            ],
            [
                "k",
                2487
            ],
            [
                "d",
                2242
            ],
            [
                "t",
                2217
            ],
            [
                "ı",
                2148
            ],
            [
                "m",
                1824
            ],
            [
                "s",
                1819
            ],
            [
                "u",
                1564
            ],
            [
                "y",
                1491
            ],
            [
                "b",
                1343
            ],
            [
                "o",
                1244
            ],
            [
                "ü",
                1220
            ],
            [
                "v",
                802
            ],
            [
                ".",
                791
            ],
            [
                "ş",
                752
            ],
            [
                "h",
                697
            ],
            [
                "z",
                611
            ],
            [
                "ç",
                541
            ],
            [
                "g",
                513
            ],
            [
                "p",
                425
            ],
            [
                ",",
                416
            ],
            [
                "c",
                388
            ],
            [
                "f",
                375
            ],
            [
                "̇",
                371
            ],
            [
                "ğ",
                360
            ],
            [
                "’",
                248
            ],
            [
                "ö",
                241
            ],
            [
                "â",
                125
            ],
            [
                "0",
                116
            ],
            [
                "1",
                100
            ],
            [
                "(",
                80
            ],
            [
                ")",
                80
            ],
            [
                ":",
                60
            ],
            [
                "8",
                58
            ],
            [
                "«",
                57
            ],
            [
                "»",
                53
            ],
            [
                "-",
                46
            ],
            [
                "5",
                38
            ],
            [
                "9",
                34
            ],
            [
                "3",
                33
            ],
            [
                "'",
                32
            ],
            [
                "j",
                27
            ],
            [
                "6",
                24
            ],
            [
                "4",
                23
            ],
            [
                "2",
                23
            ],
            [
                "7",
                23
            ],
            [
                "—",
                22
            ],
            [
                "î",
                21
            ],
            [
                ";",
                14
            ],
            [
                "û",
                14
            ],
            [
                "?",
                9
            ],
            [
                "!",
                9
            ],
            [
                "%",
                6
            ],
            [
                "★",
                5
            ],
            [
                "/",
                3
            ],
            [
                "q",
                2
            ],
            [
                "w",
                1
            ]
        ]
    },
    "1": {
        "metadata": {
            "title": "Hikayeler",
            "author": "Ömer Seyfettin",
            "processed_at": "2025-09-19T17:34:02"
        },
        "data": [
            [
                "<SPC>",
                21571
            ],
            [
                "a",
                15557
            ],
            [
                "e",
                11104
            ],
            [
                "i",
                10253
            ],
            [
                "n",
                9520
            ],
            [
                "r",
                9469
            ],
            [
                "ı",
                7571
            ],
            [
                "l",
                7420
            ],
            [
                "d",
                6421
            ],
            [
                "k",
                6353
            ],
            [
                "y",
                4779
            ],
            [
                "u",
                4608
            ],
            [
                "m",
                4319
            ],
            [
                "t",
                4281
            ],
            [
                "s",
                3790
            ],
            [
                "b",
                3785
            ],
            [
                ".",
                3629
            ],
            [
                "o",
                3024
            ],
            [
                "ü",
                2678
            ],
            [
                "ş",
                2352
            ],
            [
                ",",
                2183
            ],
            [
                "z",
                1925
            ],
            [
                "h",
                1760
            ],
            [
                "g",
                1742
            ],
            [
                "ç",
                1645
            ],
            [
                "ğ",
                1461
            ],
            [
                "v",
                1212
            ],
            [
                "c",
                1185
            ],
            [
                "ö",
                1053
            ],
            [
                "p",
                1045
            ],
            [
                "\"",
                592
            ],
            [
                "f",
                482
            ],
            [
                "-",
                482
            ],
            [
                "'",
                350
            ],
            [
                "?",
                296
            ],
            [
                "â",
                191
            ],
            [
                "!",
                186
            ],
            [
                "̇",
                181
            ],
            [
                ":",
                159
            ],
            [
                ";",
                59
            ],
            [
                "1",
                11
            ],
            [
                "j",
                9
            ],
            [
                "9",
                6
            ],
            [
                "0",
                6
            ],
            [
                "8",
                5
            ],
            [
                "(",
                3
            ],
            [
                ")",
                3
            ],
            [
                "/",
                2
            ],
            [
                "2",
                2
            ],
            [
                "4",
                2
            ],
            [
                "3",
                2
            ],
            [
                "`",
                2
            ],
            [
                "6",
                1
            ],
            [
                "w",
                1
            ],
            [
                "~",
                1
            ],
            [
                "î",
                1
            ],
            [
                "$",
                1
            ]
        ]
    },
    "2": {
        "metadata": {
            "title": "Kaşağı",
            "author": "Ömer Seyfettin",
            "processed_at": "2025-09-19T17:34:02"
        },
        "data": [
            [
                "<SPC>",
                16376
            ],
            [
                "a",
                12483
            ],
            [
                "e",
                8396
            ],
            [
                "i",
                8104
            ],
            [
                "r",
                7598
            ],
            [
                "n",
                7189
            ],
            [
                "l",
                5928
            ],
            [
                "ı",
                5448
            ],
            [
                "k",
                4849
            ],
            [
                "d",
                4659
            ],
            [
                "y",
                3825
            ],
            [
                "t",
                3701
            ],
            [
                "u",
                3602
            ],
            [
                "m",
                3581
            ],
            [
                "b",
                2976
            ],
            [
                "s",
                2826
            ],
            [
                "o",
                2748
            ],
            [
                ".",
                2356
            ],
            [
                "ü",
                2233
            ],
            [
                "ş",
                1718
            ],
            [
                ",",
                1522
            ],
            [
                "z",
                1443
            ],
            [
                "h",
                1327
            ],
            [
                "v",
                1271
            ],
            [
                "g",
                1256
            ],
            [
                "ç",
                1119
            ],
            [
                "c",
                1015
            ],
            [
                "ğ",
                964
            ],
            [
                "p",
                827
            ],
            [
                "ö",
                724
            ],
            [
                "“",
                432
            ],
            [
                "”",
                425
            ],
            [
                "f",
                424
            ],
            [
                "’",
                400
            ],
            [
                "?",
                233
            ],
            [
                "̇",
                191
            ],
            [
                ":",
                170
            ],
            [
                "!",
                126
            ],
            [
                "…",
                97
            ],
            [
                ";",
                41
            ],
            [
                "j",
                24
            ],
            [
                "‘",
                23
            ],
            [
                "-",
                13
            ],
            [
                "â",
                10
            ],
            [
                "*",
                8
            ],
            [
                "0",
                6
            ],
            [
                "(",
                5
            ],
            [
                "1",
                5
            ],
            [
                ")",
                5
            ],
            [
                "2",
                4
            ],
            [
                "w",
                3
            ],
            [
                "/",
                2
            ],
            [
                "8",
                2
            ],
            [
                "3",
                2
            ],
            [
                "–",
                2
            ],
            [
                "©",
                1
            ],
            [
                "4",
                1
            ],
            [
                "5",
                1
            ],
            [
                "6",
                1
            ],
            [
                "7",
                1
            ],
            [
                "@",
                1
            ],
            [
                "é",
                1
            ],
            [
                "q",
                1
            ]
        ]
    },
    "3": {
        "metadata": {
            "title": "Balkan Harbi Hatıraları",
            "author": "Ömer Seyfettin",
            "processed_at": "2025-09-19T17:34:03"
        },
        "data": [
            [
                "<SPC>",
                32584
            ],
            [
                "a",
                25336
            ],
            [
                "e",
                19023
            ],
            [
                "i",
                17747
            ],
            [
                "r",
                15158
            ],
            [
                "n",
                14957
            ],
            [
                "l",
                13196
            ],
            [
                "ı",
                9576
            ],
            [
                "t",
                8974
            ],
            [
                "k",
                8871
            ],
            [
                "d",
                8514
            ],
            [
                "m",
                7652
            ],
            [
                "s",
                6717
            ],
            [
                "u",
                6631
            ],
            [
                "y",
                6329
            ],
            [
                "b",
                5698
            ],
            [
                "o",
                4267
            ],
            [
                "ü",
                3828
            ],
            [
                ".",
                3671
            ],
            [
                "ş",
                3627
            ],
            [
                "h",
                3022
            ],
            [
                "z",
                2863
            ],
            [
                "v",
                2729
            ],
            [
                "g",
                2491
            ],
            [
                ",",
                2440
            ],
            [
                "ç",
                1778
            ],
            [
                "ğ",
                1747
            ],
            [
                "c",
                1677
            ],
            [
                "p",
                1571
            ],
            [
                "ö",
                1421
            ],
            [
                "f",
                1387
            ],
            [
                "’",
                1375
            ],
            [
                "1",
                1177
            ],
            [
                "9",
                552
            ],
            [
                "2",
                533
            ],
            [
                "̇",
                519
            ],
            [
                "â",
                501
            ],
            [
                "[",
                445
            ],
            [
                "]",
                445
            ],
            [
                "3",
                388
            ],
            [
                "0",
                378
            ],
            [
                "-",
                303
            ],
            [
                "8",
                243
            ],
            [
                "”",
                196
            ],
            [
                "“",
                195
            ],
            [
                "7",
                193
            ],
            [
                "6",
                185
            ],
            [
                "4",
                184
            ],
            [
                "5",
                173
            ],
            [
                ":",
                146
            ],
            [
                "î",
                124
            ],
            [
                "?",
                103
            ],
            [
                ";",
                91
            ],
            [
                "!",
                64
            ],
            [
                "(",
                61
            ],
            [
                ")",
                61
            ],
            [
                "‘",
                54
            ],
            [
                "j",
                52
            ],
            [
                "û",
                27
            ],
            [
                "–",
                16
            ],
            [
                "/",
                9
            ],
            [
                "w",
                6
            ],
            [
                "é",
                2
            ],
            [
                "*",
                2
            ],
            [
                "x",
                2
            ],
            [
                "©",
                1
            ],
            [
                "+",
                1
            ],
            [
                "•",
                1
            ],
            [
                "@",
                1
            ],
            [
                "%",
                1
            ],
            [
                "²",
                1
            ],
            [
                "ê",
                1
            ],
            [
                "q",
                1
            ],
            [
                "=",
                1
            ]
        ]
    }
}